{"get":"fixtures\/events","parameters":{"fixture":"723315"},"errors":[],"results":15,"paging":{"current":1,"total":1},"response":[{"time":{"elapsed":39,"extra":null},"team":{"id":1430,"name":"Arda Kardzhali","logo":"https:\/\/media.api-sports.io\/football\/teams\/1430.png"},"player":{"id":11149,"name":"Aleksandar Georgiev"},"assist":{"id":null,"name":null},"type":"Card","detail":"Yellow Card","comments":null},{"time":{"elapsed":44,"extra":null},"team":{"id":1430,"name":"Arda Kardzhali","logo":"https:\/\/media.api-sports.io\/football\/teams\/1430.png"},"player":{"id":10647,"name":"Deyan Lozev"},"assist":{"id":null,"name":null},"type":"Card","detail":"Yellow Card","comments":null},{"time":{"elapsed":46,"extra":null},"team":{"id":1430,"name":"Arda Kardzhali","logo":"https:\/\/media.api-sports.io\/football\/teams\/1430.png"},"player":{"id":10655,"name":"I. Kokonov"},"assist":{"id":11335,"name":"S. Kovachev"},"type":"subst","detail":"Substitution 1","comments":null},{"time":{"elapsed":46,"extra":null},"team":{"id":1430,"name":"Arda Kardzhali","logo":"https:\/\/media.api-sports.io\/football\/teams\/1430.png"},"player":{"id":10714,"name":"T. Yordanov"},"assist":{"id":9584,"name":"Juninho Piauiense"},"type":"subst","detail":"Substitution 2","comments":null},{"time":{"elapsed":60,"extra":null},"team":{"id":859,"name":"Botev Vratsa","logo":"https:\/\/media.api-sports.io\/football\/teams\/859.png"},"player":{"id":179536,"name":"M. Marinov"},"assist":{"id":291326,"name":"G. Nikolov"},"type":"subst","detail":"Substitution 1","comments":null},{"time":{"elapsed":62,"extra":null},"team":{"id":1430,"name":"Arda Kardzhali","logo":"https:\/\/media.api-sports.io\/football\/teams\/1430.png"},"player":{"id":11141,"name":"Rumen Rumenov"},"assist":{"id":null,"name":null},"type":"Card","detail":"Yellow Card","comments":null},{"time":{"elapsed":66,"extra":null},"team":{"id":1430,"name":"Arda Kardzhali","logo":"https:\/\/media.api-sports.io\/football\/teams\/1430.png"},"player":{"id":11313,"name":"I. Tilev"},"assist":{"id":11042,"name":"I. Yurukov"},"type":"subst","detail":"Substitution 3","comments":null},{"time":{"elapsed":67,"extra":null},"team":{"id":859,"name":"Botev Vratsa","logo":"https:\/\/media.api-sports.io\/football\/teams\/859.png"},"player":{"id":11004,"name":"Yoan Baurenski"},"assist":{"id":null,"name":null},"type":"Card","detail":"Yellow Card","comments":null},{"time":{"elapsed":71,"extra":null},"team":{"id":859,"name":"Botev Vratsa","logo":"https:\/\/media.api-sports.io\/football\/teams\/859.png"},"player":{"id":323484,"name":"K. Todorov"},"assist":{"id":10593,"name":"A. Georgiev"},"type":"subst","detail":"Substitution 2","comments":null},{"time":{"elapsed":87,"extra":null},"team":{"id":859,"name":"Botev Vratsa","logo":"https:\/\/media.api-sports.io\/football\/teams\/859.png"},"player":{"id":33891,"name":"D. Babunski"},"assist":{"id":10620,"name":"N. Gavov"},"type":"subst","detail":"Substitution 3","comments":null},{"time":{"elapsed":88,"extra":null},"team":{"id":859,"name":"Botev Vratsa","logo":"https:\/\/media.api-sports.io\/football\/teams\/859.png"},"player":{"id":10683,"name":"V. Vasilev"},"assist":{"id":96510,"name":"Gon\u00e7alo Vieira"},"type":"subst","detail":"Substitution 4","comments":null},{"time":{"elapsed":88,"extra":null},"team":{"id":859,"name":"Botev Vratsa","logo":"https:\/\/media.api-sports.io\/football\/teams\/859.png"},"player":{"id":11004,"name":"Y. Baurenski"},"assist":{"id":324567,"name":"T. Georgiev"},"type":"subst","detail":"Substitution 5","comments":null},{"time":{"elapsed":90,"extra":1},"team":{"id":859,"name":"Botev Vratsa","logo":"https:\/\/media.api-sports.io\/football\/teams\/859.png"},"player":{"id":11077,"name":"Kostadin Nichev"},"assist":{"id":null,"name":null},"type":"Card","detail":"Yellow Card","comments":null},{"time":{"elapsed":90,"extra":3},"team":{"id":1430,"name":"Arda Kardzhali","logo":"https:\/\/media.api-sports.io\/football\/teams\/1430.png"},"player":{"id":10890,"name":"Milen Stoev"},"assist":{"id":null,"name":null},"type":"Card","detail":"Yellow Card","comments":null},{"time":{"elapsed":90,"extra":1},"team":{"id":1430,"name":"Arda Kardzhali","logo":"https:\/\/media.api-sports.io\/football\/teams\/1430.png"},"player":{"id":10637,"name":"Plamen Krumov"},"assist":{"id":null,"name":null},"type":"Card","detail":"Yellow Card","comments":null}]}