{"get":"fixtures\/events","parameters":{"fixture":"770950"},"errors":[],"results":5,"paging":{"current":1,"total":1},"response":[{"time":{"elapsed":62,"extra":null},"team":{"id":634,"name":"Botev Plovdiv","logo":"https:\/\/media.api-sports.io\/football\/teams\/634.png"},"player":{"id":9881,"name":"Marquinhos"},"assist":{"id":129960,"name":"D. Tonev"},"type":"subst","detail":"Substitution 1","comments":null},{"time":{"elapsed":62,"extra":null},"team":{"id":634,"name":"Botev Plovdiv","logo":"https:\/\/media.api-sports.io\/football\/teams\/634.png"},"player":{"id":10975,"name":"N. Minkov"},"assist":{"id":11080,"name":"S. Rabotov"},"type":"subst","detail":"Substitution 2","comments":null},{"time":{"elapsed":71,"extra":null},"team":{"id":1416,"name":"Lokomotiv Sofia","logo":"https:\/\/media.api-sports.io\/football\/teams\/1416.png"},"player":{"id":40926,"name":"Plamen Krachunov"},"assist":{"id":null,"name":null},"type":"Card","detail":"Yellow Card","comments":null},{"time":{"elapsed":87,"extra":null},"team":{"id":634,"name":"Botev Plovdiv","logo":"https:\/\/media.api-sports.io\/football\/teams\/634.png"},"player":{"id":11103,"name":"Viktor Genev"},"assist":{"id":null,"name":null},"type":"Card","detail":"Yellow Card","comments":null},{"time":{"elapsed":89,"extra":null},"team":{"id":1416,"name":"Lokomotiv Sofia","logo":"https:\/\/media.api-sports.io\/football\/teams\/1416.png"},"player":{"id":10812,"name":"A. Aleksandrov"},"assist":{"id":304283,"name":"R. Lolala"},"type":"subst","detail":"Substitution 1","comments":null}]}