{"get":"fixtures\/events","parameters":{"fixture":"771000"},"errors":[],"results":23,"paging":{"current":1,"total":1},"response":[{"time":{"elapsed":15,"extra":null},"team":{"id":853,"name":"CSKA Sofia","logo":"https:\/\/media.api-sports.io\/football\/teams\/853.png"},"player":{"id":24217,"name":"Bradley Mazikou"},"assist":{"id":null,"name":null},"type":"Card","detail":"Yellow Card","comments":null},{"time":{"elapsed":43,"extra":null},"team":{"id":854,"name":"Slavia Sofia","logo":"https:\/\/media.api-sports.io\/football\/teams\/854.png"},"player":{"id":11227,"name":"G. Petkov"},"assist":{"id":356764,"name":"D. Zhekov"},"type":"subst","detail":"Substitution 1","comments":null},{"time":{"elapsed":46,"extra":null},"team":{"id":853,"name":"CSKA Sofia","logo":"https:\/\/media.api-sports.io\/football\/teams\/853.png"},"player":{"id":19716,"name":"Y. Wildschut"},"assist":{"id":201201,"name":"Garcez"},"type":"subst","detail":"Substitution 1","comments":null},{"time":{"elapsed":55,"extra":null},"team":{"id":854,"name":"Slavia Sofia","logo":"https:\/\/media.api-sports.io\/football\/teams\/854.png"},"player":{"id":71146,"name":"Jon Bakero"},"assist":{"id":null,"name":null},"type":"Goal","detail":"Normal Goal","comments":null},{"time":{"elapsed":60,"extra":null},"team":{"id":853,"name":"CSKA Sofia","logo":"https:\/\/media.api-sports.io\/football\/teams\/853.png"},"player":{"id":20400,"name":"Graham Carey"},"assist":{"id":null,"name":null},"type":"Card","detail":"Yellow Card","comments":null},{"time":{"elapsed":61,"extra":null},"team":{"id":853,"name":"CSKA Sofia","logo":"https:\/\/media.api-sports.io\/football\/teams\/853.png"},"player":{"id":36919,"name":"T. Lam"},"assist":{"id":20699,"name":"A. Youga"},"type":"subst","detail":"Substitution 2","comments":null},{"time":{"elapsed":61,"extra":null},"team":{"id":853,"name":"CSKA Sofia","logo":"https:\/\/media.api-sports.io\/football\/teams\/853.png"},"player":{"id":11246,"name":"G. Yomov"},"assist":{"id":85070,"name":"Y. Bai"},"type":"subst","detail":"Substitution 3","comments":null},{"time":{"elapsed":63,"extra":null},"team":{"id":853,"name":"CSKA Sofia","logo":"https:\/\/media.api-sports.io\/football\/teams\/853.png"},"player":{"id":16590,"name":"J. Caicedo"},"assist":{"id":null,"name":null},"type":"Goal","detail":"Normal Goal","comments":null},{"time":{"elapsed":65,"extra":null},"team":{"id":854,"name":"Slavia Sofia","logo":"https:\/\/media.api-sports.io\/football\/teams\/854.png"},"player":{"id":11235,"name":"Ertan Tombak"},"assist":{"id":null,"name":null},"type":"Card","detail":"Yellow Card","comments":null},{"time":{"elapsed":72,"extra":null},"team":{"id":853,"name":"CSKA Sofia","logo":"https:\/\/media.api-sports.io\/football\/teams\/853.png"},"player":{"id":38689,"name":"M. Koch"},"assist":{"id":null,"name":null},"type":"Goal","detail":"Normal Goal","comments":null},{"time":{"elapsed":73,"extra":null},"team":{"id":854,"name":"Slavia Sofia","logo":"https:\/\/media.api-sports.io\/football\/teams\/854.png"},"player":{"id":11091,"name":"K. Dobrev"},"assist":{"id":127544,"name":"M. Atanasov"},"type":"subst","detail":"Substitution 2","comments":null},{"time":{"elapsed":75,"extra":null},"team":{"id":854,"name":"Slavia Sofia","logo":"https:\/\/media.api-sports.io\/football\/teams\/854.png"},"player":{"id":127544,"name":"Martin Atanasov"},"assist":{"id":null,"name":null},"type":"Card","detail":"Yellow Card","comments":null},{"time":{"elapsed":78,"extra":null},"team":{"id":853,"name":"CSKA Sofia","logo":"https:\/\/media.api-sports.io\/football\/teams\/853.png"},"player":{"id":20699,"name":"A. Youga"},"assist":{"id":null,"name":null},"type":"Goal","detail":"Normal Goal","comments":null},{"time":{"elapsed":80,"extra":null},"team":{"id":854,"name":"Slavia Sofia","logo":"https:\/\/media.api-sports.io\/football\/teams\/854.png"},"player":{"id":78093,"name":"E. Dost"},"assist":{"id":null,"name":null},"type":"Goal","detail":"Normal Goal","comments":null},{"time":{"elapsed":82,"extra":null},"team":{"id":854,"name":"Slavia Sofia","logo":"https:\/\/media.api-sports.io\/football\/teams\/854.png"},"player":{"id":20771,"name":"Ludovic Soares"},"assist":{"id":null,"name":null},"type":"Card","detail":"Yellow Card","comments":null},{"time":{"elapsed":83,"extra":null},"team":{"id":854,"name":"Slavia Sofia","logo":"https:\/\/media.api-sports.io\/football\/teams\/854.png"},"player":{"id":71146,"name":"Jon Bakero"},"assist":{"id":291840,"name":"M. Sorakov"},"type":"subst","detail":"Substitution 3","comments":null},{"time":{"elapsed":83,"extra":null},"team":{"id":854,"name":"Slavia Sofia","logo":"https:\/\/media.api-sports.io\/football\/teams\/854.png"},"player":{"id":10633,"name":"T. Tasev"},"assist":{"id":11250,"name":"D. Stoyanov"},"type":"subst","detail":"Substitution 4","comments":null},{"time":{"elapsed":84,"extra":null},"team":{"id":854,"name":"Slavia Sofia","logo":"https:\/\/media.api-sports.io\/football\/teams\/854.png"},"player":{"id":11235,"name":"Ertan Tombak"},"assist":{"id":null,"name":null},"type":"Card","detail":"Red Card","comments":null},{"time":{"elapsed":84,"extra":null},"team":{"id":854,"name":"Slavia Sofia","logo":"https:\/\/media.api-sports.io\/football\/teams\/854.png"},"player":{"id":11235,"name":"Ertan Tombak"},"assist":{"id":null,"name":null},"type":"Card","detail":"Yellow Card","comments":null},{"time":{"elapsed":90,"extra":3},"team":{"id":853,"name":"CSKA Sofia","logo":"https:\/\/media.api-sports.io\/football\/teams\/853.png"},"player":{"id":20400,"name":"Graham Carey"},"assist":{"id":null,"name":null},"type":"Card","detail":"Red Card","comments":null},{"time":{"elapsed":90,"extra":null},"team":{"id":853,"name":"CSKA Sofia","logo":"https:\/\/media.api-sports.io\/football\/teams\/853.png"},"player":{"id":16590,"name":"J. Caicedo"},"assist":{"id":281227,"name":"B. Kwarema"},"type":"subst","detail":"Substitution 4","comments":null},{"time":{"elapsed":90,"extra":3},"team":{"id":853,"name":"CSKA Sofia","logo":"https:\/\/media.api-sports.io\/football\/teams\/853.png"},"player":{"id":20400,"name":"Graham Carey"},"assist":{"id":null,"name":null},"type":"Card","detail":"Yellow Card","comments":null},{"time":{"elapsed":90,"extra":5},"team":{"id":853,"name":"CSKA Sofia","logo":"https:\/\/media.api-sports.io\/football\/teams\/853.png"},"player":{"id":281227,"name":"Bismark Charles Sie"},"assist":{"id":null,"name":null},"type":"Card","detail":"Yellow Card","comments":null}]}