{"get":"fixtures\/lineups","parameters":{"fixture":"770921"},"errors":[],"results":2,"paging":{"current":1,"total":1},"response":[{"team":{"id":1426,"name":"CSKA 1948","logo":"https:\/\/media.api-sports.io\/football\/teams\/1426.png","colors":{"player":{"primary":"d00e1e","number":"ffffff","border":"fafb00"},"goalkeeper":{"primary":"000000","number":"000000","border":"fafb00"}}},"coach":{"id":2559,"name":"N. Kirov","photo":"https:\/\/media.api-sports.io\/football\/coachs\/2559.png"},"formation":"4-2-3-1","startXI":[{"player":{"id":1056,"name":"D. Naumov","number":29,"pos":"G","grid":"1:1"}},{"player":{"id":90610,"name":"S. Petrov","number":87,"pos":"D","grid":"2:4"}},{"player":{"id":28624,"name":"Galin Ivanov","number":33,"pos":"M","grid":"2:3"}},{"player":{"id":11053,"name":"G. Angelov","number":25,"pos":"M","grid":"2:2"}},{"player":{"id":31552,"name":"I. Chochev","number":18,"pos":"M","grid":"2:1"}},{"player":{"id":11144,"name":"K. Stoyanov","number":77,"pos":"D","grid":"3:2"}},{"player":{"id":10647,"name":"D. Lozev","number":6,"pos":"M","grid":"3:1"}},{"player":{"id":78108,"name":"I. Klimentov","number":8,"pos":"M","grid":"4:3"}},{"player":{"id":10686,"name":"D. Aleksandrov","number":11,"pos":"F","grid":"4:2"}},{"player":{"id":11317,"name":"G. Rusev","number":10,"pos":"F","grid":"4:1"}},{"player":{"id":10926,"name":"A. Bastunov","number":20,"pos":"F","grid":"5:1"}}],"substitutes":[{"player":{"id":11076,"name":"L. Marin","number":24,"pos":"M","grid":null}},{"player":{"id":11079,"name":"D. Pirgov","number":3,"pos":"D","grid":null}},{"player":{"id":10901,"name":"M. Topuzov","number":7,"pos":"M","grid":null}},{"player":{"id":137056,"name":"D. Angelov","number":9,"pos":"F","grid":null}},{"player":{"id":10750,"name":"D. Todorov","number":1,"pos":"G","grid":null}},{"player":{"id":137420,"name":"S. Dobrev","number":61,"pos":"M","grid":null}},{"player":{"id":10852,"name":"V. Yoskov","number":98,"pos":"F","grid":null}}]},{"team":{"id":1413,"name":"Tsarsko Selo","logo":"https:\/\/media.api-sports.io\/football\/teams\/1413.png","colors":{"player":{"primary":"ffffff","number":"ff0000","border":"33ff00"},"goalkeeper":{"primary":"33ff00","number":"ffffff","border":"33ff00"}}},"coach":{"id":2886,"name":"A. Zdravkov","photo":"https:\/\/media.api-sports.io\/football\/coachs\/2886.png"},"formation":"4-2-3-1","startXI":[{"player":{"id":11290,"name":"Y. Georgiev","number":1,"pos":"G","grid":"1:1"}},{"player":{"id":11133,"name":"V. Vasilev","number":26,"pos":"D","grid":"2:4"}},{"player":{"id":11047,"name":"I. Bandalovski","number":6,"pos":"D","grid":"2:3"}},{"player":{"id":10663,"name":"A. Aleksandrov","number":7,"pos":"D","grid":"2:2"}},{"player":{"id":11330,"name":"H. Popadiyn","number":14,"pos":"D","grid":"2:1"}},{"player":{"id":11083,"name":"L. Baltanov","number":10,"pos":"M","grid":"3:2"}},{"player":{"id":11160,"name":"P. Atanasov","number":20,"pos":"F","grid":"3:1"}},{"player":{"id":11136,"name":"N. Kolev","number":17,"pos":"M","grid":"4:3"}},{"player":{"id":45482,"name":"M. Joki\u0107","number":22,"pos":"M","grid":"4:2"}},{"player":{"id":11095,"name":"V. Shopov","number":93,"pos":"M","grid":"4:1"}},{"player":{"id":63587,"name":"G. Missi Mezu","number":11,"pos":"F","grid":"5:1"}}],"substitutes":[{"player":{"id":11155,"name":"M. Kavdanski","number":3,"pos":"D","grid":null}},{"player":{"id":40291,"name":"A. Stevanovi\u0107","number":8,"pos":"M","grid":null}},{"player":{"id":107699,"name":"Lucas Dias","number":89,"pos":"F","grid":null}},{"player":{"id":11147,"name":"M. Angelov","number":9,"pos":"F","grid":null}},{"player":{"id":315247,"name":"B. Tomovski","number":13,"pos":null,"grid":null}},{"player":{"id":264395,"name":"D. Georgiev","number":4,"pos":"D","grid":null}},{"player":{"id":11178,"name":"H. Vasilev","number":30,"pos":"G","grid":null}}]}]}